mcp_lance_db/__init__.py
mcp_lance_db/__main__.py
mcp_lance_db/db_client.py
mcp_lance_db/server.py
mcp_lance_db-0.1.6.dist-info/METADATA
mcp_lance_db-0.1.6.dist-info/WHEEL
mcp_lance_db-0.1.6.dist-info/entry_points.txt
mcp_lance_db-0.1.6.dist-info/RECORD
