Metadata-Version: 2.4
Name: mcp-lance-db
Version: 0.1.6
Summary: mcp-lance-db
Author-email: truskovskiyk <truskovskiyk@gmail.com>
Requires-Python: >=3.12
Requires-Dist: ipython>=8.32.0
Requires-Dist: lancedb>=0.19.0
Requires-Dist: mcp[cli]==1.3.0
Requires-Dist: ruff>=0.9.7
Requires-Dist: sentence-transformers>=3.4.1
Provides-Extra: test
Requires-Dist: pytest-asyncio>=0.23.5; extra == 'test'
Requires-Dist: pytest-cov>=4.1.0; extra == 'test'
Requires-Dist: pytest>=8.0.0; extra == 'test'
